{
	"version": "1.13.0",
	"tipsConfig": {
		"daysLeftBeforeGeneralTip": 3,
		"firstTimeMinDaysToRemind": 4,
		"firstTimeMaxDaysToRemind": 6,
		"minDaysToRemind": 6,
		"maxDaysToRemind": 10,
		"daysAfterLastUsage": 30,
		"allTipsShownFirstly": false,
		"tips": {
			"generalTips": {
				"elementInspector": {},
				"logCatMonitor": {},
				"networkInspector": {},
				"directDebuggingWithHermes": {
					"shownDate": "2025-05-07T09:47:17.909Z"
				},
				"debuggingRNWAndMacOSApps": {},
				"expoHostType": {},
				"customEnvVariables": {}
			},
			"specificTips": {
				"networkInspectorLogsColorTheme": {}
			}
		},
		"lastExtensionUsageDate": "2026-01-09T09:00:51.875Z"
	},
	"surveyConfig": {
		"shortPeriodToRemind": 30,
		"longPeriodToRemind": 90,
		"popCoveragePercent": 0.1,
		"enabled": true,
		"daysLeftBeforeSurvey": 27,
		"surveyName": "userSatisfactionSurvey",
		"surveyUrl": "https://www.surveymonkey.com/r/6FJGVDV",
		"lastExtensionUsageDate": "2026-01-09T09:00:52.626Z"
	}
}